pgsql_parser/__init__.py
pgsql_parser/models.py
pgsql_parser/parser_base.py
pgsql_parser/sql_lexer.py
pgsql_parser/sql_parser.py
pgsql_parser/sqlparser.py
python_pgsql_parser-0.2.0.dist-info/licenses/LICENSE
python_pgsql_parser-0.2.0.dist-info/METADATA
python_pgsql_parser-0.2.0.dist-info/WHEEL
python_pgsql_parser-0.2.0.dist-info/top_level.txt
python_pgsql_parser-0.2.0.dist-info/RECORD
