Metadata-Version: 2.4
Name: python-pgsql-parser
Version: 0.2.0
Summary: Advanced PostgreSQL SQL parser for extracting database schema metadata
Home-page: https://github.com/yourusername/python-pgsql-parser
Author: Sunny Liu
Author-email: Sunny Liu <sunnyliu2@gmail.com>
License: MIT
Project-URL: Homepage, https://github.com/devsunny/python-pgsql-parser
Project-URL: Documentation, https://github.com/devsunny/python-pgsql-parser/blob/main/docs/index.md
Project-URL: Source, https://github.com/devsunny/python-pgsql-parser
Project-URL: Tracker, https://github.com/devsunny/python-pgsql-parser/issues
Keywords: sql,parser,postgresql,ddl,metadata,schema,analysis
Classifier: Development Status :: 4 - Beta
Classifier: Intended Audience :: Developers
Classifier: Intended Audience :: Science/Research
Classifier: Intended Audience :: Information Technology
Classifier: License :: OSI Approved :: MIT License
Classifier: Programming Language :: Python :: 3
Classifier: Programming Language :: Python :: 3.7
Classifier: Programming Language :: Python :: 3.8
Classifier: Programming Language :: Python :: 3.9
Classifier: Programming Language :: Python :: 3.10
Classifier: Programming Language :: Python :: 3.11
Classifier: Operating System :: OS Independent
Classifier: Topic :: Database
Classifier: Topic :: Software Development :: Libraries :: Python Modules
Classifier: Topic :: Scientific/Engineering :: Information Analysis
Requires-Python: >=3.7
License-File: LICENSE
Dynamic: author
Dynamic: home-page
Dynamic: license-file
Dynamic: requires-python
